shc/__init__.py
shc/py.typed
shc/blocks/__init__.py
shc/blocks/attention.py
shc/blocks/feedforward.py
shc/blocks/shc_block.py
shc/configs/__init__.py
shc/configs/config.py
shc/data/__init__.py
shc/data/dataloader.py
shc/data/dataset.py
shc/evaluation/__init__.py
shc/evaluation/benchmarks.py
shc/evaluation/metrics.py
shc/evaluation/profiler.py
shc/layers/__init__.py
shc/layers/adaptive_rank.py
shc/layers/base.py
shc/layers/cayley.py
shc/layers/factorized_cache.py
shc/layers/sparse_mixture.py
shc/models/__init__.py
shc/models/base.py
shc/models/embeddings.py
shc/models/ssm_student.py
shc/models/transformer.py
shc/scripts/__init__.py
shc/scripts/evaluate.py
shc/scripts/train.py
shc/training/__init__.py
shc/training/distillation.py
shc/training/distributed.py
shc/training/optimizer.py
shc/training/trainer.py
sparse_hyper_connections-0.1.0.dist-info/licenses/LICENSE
sparse_hyper_connections-0.1.0.dist-info/METADATA
sparse_hyper_connections-0.1.0.dist-info/WHEEL
sparse_hyper_connections-0.1.0.dist-info/entry_points.txt
sparse_hyper_connections-0.1.0.dist-info/top_level.txt
sparse_hyper_connections-0.1.0.dist-info/RECORD
